{
  "entrypoints": {
    "app": {
      "js": [
        "/assets/0.f0f1d94b.js",
        "/assets/3.475a119c.js",
        "/assets/app.3fcc1efd.js"
      ],
      "css": [
        "/assets/3.3ce09104.css",
        "/assets/app.7eb9e758.css"
      ]
    },
    "page_index": {
      "js": [
        "/assets/0.f0f1d94b.js",
        "/assets/1.5ec9dd31.js",
        "/assets/page_index.3d4da071.js"
      ],
      "css": [
        "/assets/1.04b85e3d.css",
        "/assets/page_index.e0319903.css"
      ]
    },
    "graph_form": {
      "js": [
        "/assets/0.f0f1d94b.js",
        "/assets/1.5ec9dd31.js",
        "/assets/graph_form.be182736.js"
      ],
      "css": [
        "/assets/1.04b85e3d.css",
        "/assets/graph_form.3a3f71f6.css"
      ]
    },
    "graph_list": {
      "js": [
        "/assets/0.f0f1d94b.js",
        "/assets/1.5ec9dd31.js",
        "/assets/graph_list.4fb2b6f4.js"
      ],
      "css": [
        "/assets/1.04b85e3d.css",
        "/assets/graph_list.3a3f71f6.css"
      ]
    },
    "logview_form": {
      "js": [
        "/assets/0.f0f1d94b.js",
        "/assets/1.5ec9dd31.js",
        "/assets/logview_form.a4a37122.js"
      ],
      "css": [
        "/assets/1.04b85e3d.css",
        "/assets/logview_form.3a3f71f6.css"
      ]
    },
    "user_list": {
      "js": [
        "/assets/0.f0f1d94b.js",
        "/assets/1.5ec9dd31.js",
        "/assets/user_list.fddcb926.js"
      ],
      "css": [
        "/assets/1.04b85e3d.css",
        "/assets/user_list.3a3f71f6.css"
      ]
    },
    "user_confirmation": {
      "js": [
        "/assets/0.f0f1d94b.js",
        "/assets/1.5ec9dd31.js",
        "/assets/user_confirmation.801e7acd.js"
      ],
      "css": [
        "/assets/1.04b85e3d.css",
        "/assets/user_confirmation.3a3f71f6.css"
      ]
    },
    "user_profile": {
      "js": [
        "/assets/0.f0f1d94b.js",
        "/assets/1.5ec9dd31.js",
        "/assets/user_profile.ddf7a73d.js"
      ],
      "css": [
        "/assets/1.04b85e3d.css",
        "/assets/user_profile.674e28b3.css"
      ]
    },
    "navbar": {
      "js": [
        "/assets/0.f0f1d94b.js",
        "/assets/1.5ec9dd31.js",
        "/assets/navbar.7de8283f.js"
      ],
      "css": [
        "/assets/1.04b85e3d.css",
        "/assets/navbar.3a3f71f6.css"
      ]
    },
    "sidebar_component": {
      "js": [
        "/assets/0.f0f1d94b.js",
        "/assets/1.5ec9dd31.js",
        "/assets/sidebar_component.75ffa199.js"
      ],
      "css": [
        "/assets/1.04b85e3d.css",
        "/assets/sidebar_component.3a3f71f6.css"
      ]
    },
    "js_grid": {
      "js": [
        "/assets/0.f0f1d94b.js",
        "/assets/1.5ec9dd31.js",
        "/assets/js_grid.e9521d04.js"
      ],
      "css": [
        "/assets/1.04b85e3d.css",
        "/assets/js_grid.17bdf01c.css"
      ]
    },
    "flot_chart": {
      "js": [
        "/assets/0.f0f1d94b.js",
        "/assets/1.5ec9dd31.js",
        "/assets/flot_chart.a76f3dcd.js"
      ],
      "css": [
        "/assets/1.04b85e3d.css",
        "/assets/flot_chart.61c0eef4.css"
      ]
    },
    "welcome-page": {
      "js": [
        "/assets/0.f0f1d94b.js",
        "/assets/1.5ec9dd31.js",
        "/assets/welcome-page.adb3c57f.js"
      ],
      "css": [
        "/assets/1.04b85e3d.css",
        "/assets/welcome-page.1932c9bd.css"
      ]
    },
    "page_login": {
      "js": [
        "/assets/0.f0f1d94b.js",
        "/assets/1.5ec9dd31.js",
        "/assets/page_login.41c66042.js"
      ],
      "css": [
        "/assets/1.04b85e3d.css",
        "/assets/page_login.53c5a1b7.css"
      ]
    },
    "page_forgot": {
      "js": [
        "/assets/0.f0f1d94b.js",
        "/assets/1.5ec9dd31.js",
        "/assets/page_forgot.8b5dc1ba.js"
      ],
      "css": [
        "/assets/1.04b85e3d.css",
        "/assets/page_forgot.50c00b15.css"
      ]
    },
    "page_reset": {
      "js": [
        "/assets/0.f0f1d94b.js",
        "/assets/1.5ec9dd31.js",
        "/assets/page_reset.2a87407f.js"
      ],
      "css": [
        "/assets/1.04b85e3d.css",
        "/assets/page_reset.3a3f71f6.css"
      ]
    },
    "dashboard_list": {
      "js": [
        "/assets/0.f0f1d94b.js",
        "/assets/1.5ec9dd31.js",
        "/assets/dashboard_list.2ca574cc.js"
      ],
      "css": [
        "/assets/1.04b85e3d.css",
        "/assets/dashboard_list.3a3f71f6.css"
      ]
    },
    "dashboard_form": {
      "js": [
        "/assets/0.f0f1d94b.js",
        "/assets/1.5ec9dd31.js",
        "/assets/dashboard_form.86307db5.js"
      ],
      "css": [
        "/assets/1.04b85e3d.css",
        "/assets/dashboard_form.3a3f71f6.css"
      ]
    },
    "widget_list": {
      "js": [
        "/assets/0.f0f1d94b.js",
        "/assets/1.5ec9dd31.js",
        "/assets/widget_list.10f58f7e.js"
      ],
      "css": [
        "/assets/1.04b85e3d.css",
        "/assets/widget_list.3a3f71f6.css"
      ]
    },
    "widget_form": {
      "js": [
        "/assets/0.f0f1d94b.js",
        "/assets/1.5ec9dd31.js",
        "/assets/widget_form.673198f5.js"
      ],
      "css": [
        "/assets/1.04b85e3d.css",
        "/assets/widget_form.3a3f71f6.css"
      ]
    },
    "dashboard-page": {
      "js": [
        "/assets/0.f0f1d94b.js",
        "/assets/1.5ec9dd31.js",
        "/assets/dashboard-page.e90f3960.js"
      ],
      "css": [
        "/assets/1.04b85e3d.css",
        "/assets/dashboard-page.3a3f71f6.css"
      ]
    },
    "alerts_list": {
      "js": [
        "/assets/0.f0f1d94b.js",
        "/assets/1.5ec9dd31.js",
        "/assets/alerts_list.1e248d13.js"
      ],
      "css": [
        "/assets/1.04b85e3d.css",
        "/assets/alerts_list.3a3f71f6.css"
      ]
    },
    "export_list": {
      "js": [
        "/assets/0.f0f1d94b.js",
        "/assets/1.5ec9dd31.js",
        "/assets/export_list.8afe91a0.js"
      ],
      "css": [
        "/assets/1.04b85e3d.css",
        "/assets/export_list.3a3f71f6.css"
      ]
    }
  }
}