{
  "entrypoints": {
    "app": {
      "js": [
        "/assets/1.2ab0b88f.js",
        "/assets/3.34ee1439.js",
        "/assets/app.2a273a63.js"
      ],
      "css": [
        "/assets/3.9e8fc629.css",
        "/assets/app.08791552.css"
      ]
    },
    "page_index": {
      "js": [
        "/assets/0.e665c24c.js",
        "/assets/1.2ab0b88f.js",
        "/assets/page_index.6fe321a2.js"
      ],
      "css": [
        "/assets/page_index.b4a11d9d.css"
      ]
    },
    "database_tables": {
      "js": [
        "/assets/0.e665c24c.js",
        "/assets/1.2ab0b88f.js",
        "/assets/database_tables.30a38868.js"
      ],
      "css": [
        "/assets/database_tables.9d6b9b59.css"
      ]
    },
    "database_form": {
      "js": [
        "/assets/0.e665c24c.js",
        "/assets/1.2ab0b88f.js",
        "/assets/database_form.12adcc22.js"
      ],
      "css": [
        "/assets/database_form.9d6b9b59.css"
      ]
    },
    "graph_form": {
      "js": [
        "/assets/0.e665c24c.js",
        "/assets/1.2ab0b88f.js",
        "/assets/graph_form.3a142494.js"
      ],
      "css": [
        "/assets/graph_form.9d6b9b59.css"
      ]
    },
    "graph_list": {
      "js": [
        "/assets/0.e665c24c.js",
        "/assets/1.2ab0b88f.js",
        "/assets/graph_list.72bbf4a9.js"
      ],
      "css": [
        "/assets/graph_list.9d6b9b59.css"
      ]
    },
    "logview_form": {
      "js": [
        "/assets/0.e665c24c.js",
        "/assets/1.2ab0b88f.js",
        "/assets/logview_form.3e4d68b8.js"
      ],
      "css": [
        "/assets/logview_form.9d6b9b59.css"
      ]
    },
    "user_list": {
      "js": [
        "/assets/0.e665c24c.js",
        "/assets/1.2ab0b88f.js",
        "/assets/user_list.b9d60f3f.js"
      ],
      "css": [
        "/assets/user_list.9d6b9b59.css"
      ]
    },
    "user_form": {
      "js": [
        "/assets/0.e665c24c.js",
        "/assets/1.2ab0b88f.js",
        "/assets/user_form.1f1c0b9a.js"
      ],
      "css": [
        "/assets/user_form.9d6b9b59.css"
      ]
    },
    "user_confirmation": {
      "js": [
        "/assets/0.e665c24c.js",
        "/assets/1.2ab0b88f.js",
        "/assets/user_confirmation.313b41d0.js"
      ],
      "css": [
        "/assets/user_confirmation.9d6b9b59.css"
      ]
    },
    "user_profile": {
      "js": [
        "/assets/0.e665c24c.js",
        "/assets/1.2ab0b88f.js",
        "/assets/user_profile.5c3f9f7f.js"
      ],
      "css": [
        "/assets/user_profile.9d6b9b59.css"
      ]
    },
    "navbar": {
      "js": [
        "/assets/0.e665c24c.js",
        "/assets/1.2ab0b88f.js",
        "/assets/navbar.dee6ba4e.js"
      ],
      "css": [
        "/assets/navbar.9d6b9b59.css"
      ]
    },
    "sidebar": {
      "js": [
        "/assets/0.e665c24c.js",
        "/assets/1.2ab0b88f.js",
        "/assets/sidebar.d9369be1.js"
      ],
      "css": [
        "/assets/sidebar.9d6b9b59.css"
      ]
    },
    "js_grid": {
      "js": [
        "/assets/0.e665c24c.js",
        "/assets/1.2ab0b88f.js",
        "/assets/js_grid.ef3e16c8.js"
      ],
      "css": [
        "/assets/js_grid.9f86c2e8.css"
      ]
    },
    "flot_chart": {
      "js": [
        "/assets/0.e665c24c.js",
        "/assets/1.2ab0b88f.js",
        "/assets/flot_chart.0364b172.js"
      ],
      "css": [
        "/assets/flot_chart.9c6eecc5.css"
      ]
    },
    "content-header": {
      "js": [
        "/assets/0.e665c24c.js",
        "/assets/content-header.ff7e1838.js"
      ]
    },
    "welcome-page": {
      "js": [
        "/assets/0.e665c24c.js",
        "/assets/1.2ab0b88f.js",
        "/assets/welcome-page.066883e3.js"
      ],
      "css": [
        "/assets/welcome-page.b500a9e6.css"
      ]
    },
    "page_login": {
      "js": [
        "/assets/0.e665c24c.js",
        "/assets/1.2ab0b88f.js",
        "/assets/page_login.8553e3d5.js"
      ],
      "css": [
        "/assets/page_login.9d6b9b59.css"
      ]
    },
    "page_forgot": {
      "js": [
        "/assets/0.e665c24c.js",
        "/assets/1.2ab0b88f.js",
        "/assets/page_forgot.a52c94f8.js"
      ],
      "css": [
        "/assets/page_forgot.9d6b9b59.css"
      ]
    },
    "page_reset": {
      "js": [
        "/assets/0.e665c24c.js",
        "/assets/1.2ab0b88f.js",
        "/assets/page_reset.dc769054.js"
      ],
      "css": [
        "/assets/page_reset.9d6b9b59.css"
      ]
    },
    "page_change_password": {
      "js": [
        "/assets/0.e665c24c.js",
        "/assets/1.2ab0b88f.js",
        "/assets/page_change_password.0818e531.js"
      ],
      "css": [
        "/assets/page_change_password.9d6b9b59.css"
      ]
    },
    "dashboard_list": {
      "js": [
        "/assets/0.e665c24c.js",
        "/assets/1.2ab0b88f.js",
        "/assets/dashboard_list.9d9d37a3.js"
      ],
      "css": [
        "/assets/dashboard_list.9d6b9b59.css"
      ]
    },
    "dashboard_form": {
      "js": [
        "/assets/0.e665c24c.js",
        "/assets/1.2ab0b88f.js",
        "/assets/dashboard_form.5d8d37b1.js"
      ],
      "css": [
        "/assets/dashboard_form.9d6b9b59.css"
      ]
    },
    "widget_list": {
      "js": [
        "/assets/0.e665c24c.js",
        "/assets/1.2ab0b88f.js",
        "/assets/widget_list.02d42858.js"
      ],
      "css": [
        "/assets/widget_list.9d6b9b59.css"
      ]
    },
    "widget_form": {
      "js": [
        "/assets/0.e665c24c.js",
        "/assets/1.2ab0b88f.js",
        "/assets/widget_form.0069416e.js"
      ],
      "css": [
        "/assets/widget_form.9d6b9b59.css"
      ]
    },
    "dashboard-page": {
      "js": [
        "/assets/0.e665c24c.js",
        "/assets/1.2ab0b88f.js",
        "/assets/dashboard-page.57e8db13.js"
      ],
      "css": [
        "/assets/dashboard-page.9d6b9b59.css"
      ]
    },
    "alerts_list": {
      "js": [
        "/assets/0.e665c24c.js",
        "/assets/1.2ab0b88f.js",
        "/assets/alerts_list.2026c133.js"
      ],
      "css": [
        "/assets/alerts_list.9d6b9b59.css"
      ]
    },
    "alerts_form": {
      "js": [
        "/assets/0.e665c24c.js",
        "/assets/1.2ab0b88f.js",
        "/assets/alerts_form.a6d07192.js"
      ],
      "css": [
        "/assets/alerts_form.9d6b9b59.css"
      ]
    },
    "export_list": {
      "js": [
        "/assets/0.e665c24c.js",
        "/assets/1.2ab0b88f.js",
        "/assets/export_list.5503cd28.js"
      ],
      "css": [
        "/assets/export_list.9d6b9b59.css"
      ]
    }
  }
}